<xml xmlns="http://www.w3.org/1999/xhtml">
  <block type="oled_cleardisplay" id="380" x="315" y="73">
    <next>
      <block type="controls_repeat" id="629" inline="true">
        <value name="TIMES">
          <block type="math_number" id="636">
            <field name="NUM">20</field>
          </block>
        </value>
        <statement name="DO">
          <block type="movement_forward" id="594">
            <next>
              <block type="robot_delay" id="605" inline="true">
                <value name="DELAY">
                  <block type="math_number" id="612">
                    <field name="NUM">20</field>
                  </block>
                </value>
                <next>
                  <block type="oled_cleardisplay" id="435">
                    <next>
                      <block type="oled_drawtext" id="459">
                        <field name="TEXT">blue</field>
                        <next>
                          <block type="oled_drawnumber" id="477" inline="true">
                            <value name="NUMBER">
                              <block type="sensor_spectrometer" id="484">
                                <field name="LIGHT">BLUE</field>
                              </block>
                            </value>
                            <next>
                              <block type="oled_setcursor" id="509" inline="true">
                                <value name="STARTX">
                                  <block type="math_number" id="516">
                                    <field name="NUM">0</field>
                                  </block>
                                </value>
                                <value name="STARTY">
                                  <block type="math_number" id="517">
                                    <field name="NUM">10</field>
                                  </block>
                                </value>
                                <next>
                                  <block type="oled_cleardisplay" id="526">
                                    <next>
                                      <block type="oled_drawtext" id="561">
                                        <field name="TEXT">green</field>
                                        <next>
                                          <block type="oled_drawnumber" id="570" inline="true">
                                            <value name="NUMBER">
                                              <block type="sensor_spectrometer" id="577">
                                                <field name="LIGHT">GREEN</field>
                                              </block>
                                            </value>
                                            <next>
                                              <block type="oled_setcursor" id="582" inline="true">
                                                <value name="STARTX">
                                                  <block type="math_number" id="583">
                                                    <field name="NUM">0</field>
                                                  </block>
                                                </value>
                                                <value name="STARTY">
                                                  <block type="math_number" id="584">
                                                    <field name="NUM">20</field>
                                                  </block>
                                                </value>
                                              </block>
                                            </next>
                                          </block>
                                        </next>
                                      </block>
                                    </next>
                                  </block>
                                </next>
                              </block>
                            </next>
                          </block>
                        </next>
                      </block>
                    </next>
                  </block>
                </next>
              </block>
            </next>
          </block>
        </statement>
        <next>
          <block type="movement_stop" id="647"></block>
        </next>
      </block>
    </next>
  </block>
</xml>